CHANGES.rst
MANIFEST.in
README.rst
buildout.cfg
setup.py
versions.cfg
bobtemplates/__init__.py
bobtemplates.ecreall.egg-info/PKG-INFO
bobtemplates.ecreall.egg-info/SOURCES.txt
bobtemplates.ecreall.egg-info/dependency_links.txt
bobtemplates.ecreall.egg-info/namespace_packages.txt
bobtemplates.ecreall.egg-info/not-zip-safe
bobtemplates.ecreall.egg-info/requires.txt
bobtemplates.ecreall.egg-info/top_level.txt
bobtemplates/plone_addon/.coveragerc.bob
bobtemplates/plone_addon/.gitignore.bob
bobtemplates/plone_addon/.mrbob.ini
bobtemplates/plone_addon/.travis.yml.bob
bobtemplates/plone_addon/CHANGES.rst.bob
bobtemplates/plone_addon/CONTRIBUTORS.rst.bob
bobtemplates/plone_addon/MANIFEST.in.bob
bobtemplates/plone_addon/README.rst.bob
bobtemplates/plone_addon/bootstrap.py
bobtemplates/plone_addon/buildout.cfg
bobtemplates/plone_addon/setup.py.bob
bobtemplates/plone_addon/travis.cfg
bobtemplates/plone_addon/buildout.d/base.cfg.bob
bobtemplates/plone_addon/buildout.d/checkouts.cfg
bobtemplates/plone_addon/buildout.d/development.cfg
bobtemplates/plone_addon/buildout.d/jenkins.cfg.bob
bobtemplates/plone_addon/buildout.d/sources.cfg
bobtemplates/plone_addon/buildout.d/versions.cfg
bobtemplates/plone_addon/docs/LICENSE.GPL.bob
bobtemplates/plone_addon/docs/LICENSE.rst.bob
bobtemplates/plone_addon/src/+package.namespace+/__init__.py
bobtemplates/plone_addon/src/+package.namespace+/+package.name+/__init__.py.bob
bobtemplates/plone_addon/src/+package.namespace+/+package.name+/configure.zcml.bob
bobtemplates/plone_addon/src/+package.namespace+/+package.name+/interfaces.py.bob
bobtemplates/plone_addon/src/+package.namespace+/+package.name+/setuphandlers.py.bob
bobtemplates/plone_addon/src/+package.namespace+/+package.name+/testing.py.bob
bobtemplates/plone_addon/src/+package.namespace+/+package.name+/testing.zcml.bob
bobtemplates/plone_addon/src/+package.namespace+/+package.name+/browser/__init__.py
bobtemplates/plone_addon/src/+package.namespace+/+package.name+/browser/configure.zcml.bob
bobtemplates/plone_addon/src/+package.namespace+/+package.name+/browser/static/.gitkeep
bobtemplates/plone_addon/src/+package.namespace+/+package.name+/content/__init__.py
bobtemplates/plone_addon/src/+package.namespace+/+package.name+/content/configure.zcml.bob
