Metadata-Version: 1.1
Name: bobtemplates.ecreall
Version: 0.6
Summary: Templates for Ecréall projects.
Home-page: https://github.com/cedricmessiant/bobtemplates.ecreall
Author: Cédric Messiant
Author-email: cedricmessiant@ecreall.com
License: GPL
Platform: UNKNOWN
Classifier: Environment :: Console
Classifier: Intended Audience :: Developers
Classifier: Natural Language :: English
Classifier: Operating System :: OS Independent
Classifier: Programming Language :: Python
Classifier: Topic :: Software Development :: Code Generators
Classifier: Topic :: Utilities
